[
    {
        "id": "4f3d2423-74db-4fbc-89e4-da603b578001",
        "username": "gandaki_admin",
        "gmail": "gandaki.hospital@gmail.com",
        "password": "password123",
        "name": "Gandaki Medical College"
    },
    {
        "id": "4f3d2423-74db-4fbc-89e4-da603b578002",
        "username": "manipal_admin",
        "gmail": "manipal.hospital@gmail.com",
        "password": "password123",
        "name": "Manipal Teaching Hospital"
    },
    {
        "id": "4f3d2423-74db-4fbc-89e4-da603b578003",
        "username": "pahs_admin",
        "gmail": "pahs.hospital@gmail.com",
        "password": "password123",
        "name": "Pokhara Academy of Health Sciences"
    },
    {
        "id": "4f3d2423-74db-4fbc-89e4-da603b578004",
        "username": "metrocity_admin",
        "gmail": "metrocity.hospital@gmail.com",
        "password": "password123",
        "name": "Metrocity Hospital"
    },
    {
        "id": "4f3d2423-74db-4fbc-89e4-da603b578005",
        "username": "charak_admin",
        "gmail": "charak.hospital@gmail.com",
        "password": "password123",
        "name": "Charak Memorial Hospital"
    }
]